dianyi/API.py
dianyi/__init__.py
dianyi/camera.py
dianyi/config.py
dianyi/constraints.py
dianyi/cursor.py
dianyi/draw.py
dianyi/draw_options.py
dianyi/events.py
dianyi/facilitate.py
dianyi/game_object.py
dianyi/music.py
dianyi/physics.py
dianyi/screen.py
dianyi/settings.py
dianyi/sprite.py
dianyi/test.py
dianyi/textbox.py
dianyi/tiledmap.py
dianyi/__pycache__/API.cpython-36.pyc
dianyi/__pycache__/API.cpython-37.pyc
dianyi/__pycache__/__init__.cpython-36.pyc
dianyi/__pycache__/__init__.cpython-37.pyc
dianyi/__pycache__/camera.cpython-36.pyc
dianyi/__pycache__/camera.cpython-37.pyc
dianyi/__pycache__/config.cpython-36.pyc
dianyi/__pycache__/config.cpython-37.pyc
dianyi/__pycache__/constraints.cpython-36.pyc
dianyi/__pycache__/constraints.cpython-37.pyc
dianyi/__pycache__/draw.cpython-36.pyc
dianyi/__pycache__/draw.cpython-37.pyc
dianyi/__pycache__/draw_options.cpython-36.pyc
dianyi/__pycache__/draw_options.cpython-37.pyc
dianyi/__pycache__/events.cpython-36.pyc
dianyi/__pycache__/events.cpython-37.pyc
dianyi/__pycache__/facilitate.cpython-36.pyc
dianyi/__pycache__/facilitate.cpython-37.pyc
dianyi/__pycache__/game_object.cpython-36.pyc
dianyi/__pycache__/game_object.cpython-37.pyc
dianyi/__pycache__/music.cpython-36.pyc
dianyi/__pycache__/music.cpython-37.pyc
dianyi/__pycache__/physics.cpython-36.pyc
dianyi/__pycache__/physics.cpython-37.pyc
dianyi/__pycache__/screen.cpython-36.pyc
dianyi/__pycache__/screen.cpython-37.pyc
dianyi/__pycache__/settings.cpython-36.pyc
dianyi/__pycache__/settings.cpython-37.pyc
dianyi/__pycache__/sprite.cpython-36.pyc
dianyi/__pycache__/sprite.cpython-37.pyc
dianyi/__pycache__/textbox.cpython-36.pyc
dianyi/__pycache__/textbox.cpython-37.pyc
dianyi/__pycache__/tiledmap.cpython-36.pyc
dianyi/__pycache__/tiledmap.cpython-37.pyc
dianyi/static/DialogBox.png
dianyi/static/pymunk_logo_googlecode.png
dianyi/static/simkai.ttf
dianyi/static/simsun.ttc
yuanmaxiong1-2.0.dist-info/LICENSE
yuanmaxiong1-2.0.dist-info/METADATA
yuanmaxiong1-2.0.dist-info/WHEEL
yuanmaxiong1-2.0.dist-info/top_level.txt
yuanmaxiong1-2.0.dist-info/RECORD
