Metadata-Version: 2.1
Name: yuanmaxiong1
Version: 2.0
Summary: markdown editor
Home-page: https://markdown.felinae.net
Author: Wangzhe
Author-email: markdown@felinae.net
License: UNKNOWN
Keywords: django markdown editor editormd
Platform: UNKNOWN
Classifier: Programming Language :: Python
Classifier: Development Status :: 4 - Beta
Classifier: Operating System :: OS Independent
Classifier: License :: OSI Approved :: Apache Software License
Classifier: Framework :: Django
